README.rst
setup.py
AndrikBJavaCCF/__init__.py
AndrikBJavaCCF/__main__.py
AndrikBJavaCCF/file.py
AndrikBJavaCCF/formatter.py
AndrikBJavaCCF/lexer.py
AndrikBJavaCCF/main.py
cmdline_AndrikBJavaCCF.egg-info/PKG-INFO
cmdline_AndrikBJavaCCF.egg-info/SOURCES.txt
cmdline_AndrikBJavaCCF.egg-info/dependency_links.txt
cmdline_AndrikBJavaCCF.egg-info/entry_points.txt
cmdline_AndrikBJavaCCF.egg-info/top_level.txt