Metadata-Version: 1.0
Name: cmdline-AndrikBJavaCCF
Version: 1.0.1
Summary: Python command line application to fix java code convention.
Home-page: https://github.com/AndrikB
Author: Andrii Blahyi
Author-email: blagij00@gmail.com
License: UNKNOWN
Platform: UNKNOWN
